couchmount
