Metadata-Version: 1.0
Name: CouchDB-FUSE
Version: 0.2dev
Summary: CouchDB FUSE module
Home-page: http://code.google.com/p/couchdb-fuse/
Author: Jason Davies
Author-email: jason@jasondavies.com
License: BSD
Platform: UNKNOWN
Classifier: Development Status :: 3 - Alpha
Classifier: Intended Audience :: Developers
Classifier: License :: OSI Approved :: BSD License
Classifier: Operating System :: OS Independent
Classifier: Programming Language :: Python
Classifier: Topic :: Database :: Front-Ends
